cricpy2/.env.sample
cricpy2/__init__.py
cricpy2/cric_util.py
cricpy2/cricket.py
cricpy2/cricket_constants.py
cricpy2/knockout.py
cricpy2/template.py
cricpy2/__pycache__/__init__.cpython-310.pyc
cricpy2/__pycache__/knockout.cpython-310.pyc
cricpy2-0.1.5.dist-info/METADATA
cricpy2-0.1.5.dist-info/WHEEL
cricpy2-0.1.5.dist-info/top_level.txt
cricpy2-0.1.5.dist-info/RECORD
