Metadata-Version: 2.1
Name: cricpy2
Version: 0.1.5
Summary: A Cricket Game
Author: Featureprenuer
License: UNKNOWN
Platform: UNKNOWN
Classifier: Programming Language :: Python :: 3
Classifier: License :: OSI Approved :: MIT License
Classifier: Operating System :: OS Independent
Requires-Python: >=3.6
Requires-Dist: python-dotenv
Requires-Dist: twine
Requires-Dist: setuptools
Requires-Dist: wheel
